coronacli/__init__.py
coronacli/arguments.py
coronacli/cli.py
coronacli/config.py
coronacli/db.py
coronacli/display.py
coronacli/scraper.py
coronacli/transformer.py
coronacli/utils.py
coronacli-0.1.6.dist-info/LICENSE
coronacli-0.1.6.dist-info/METADATA
coronacli-0.1.6.dist-info/WHEEL
coronacli-0.1.6.dist-info/entry_points.txt
coronacli-0.1.6.dist-info/top_level.txt
coronacli-0.1.6.dist-info/RECORD
